{"_type":"export","__export_format":4,"__export_date":"2024-04-23T16:21:09.757Z","__export_source":"insomnia.desktop.app:v8.6.1","resources":[{"_id":"req_9357570d027b44e29f3e8b23ce1d1471","parentId":"wrk_2f69f9c44fea4e6193a68e29375454c7","modified":1713843129610,"created":1713843087544,"url":"http://localhost:3000/cars/maisModelos","name":"maisModelos","description":"","method":"GET","body":{},"parameters":[],"headers":[{"name":"User-Agent","value":"insomnia/8.6.1"}],"authentication":{},"metaSortKey":-1713843087544,"isPrivate":false,"pathParameters":[],"settingStoreCookies":true,"settingSendCookies":true,"settingDisableRenderRequestBody":false,"settingEncodeUrl":true,"settingRebuildPath":true,"settingFollowRedirects":"global","_type":"request"},{"_id":"wrk_2f69f9c44fea4e6193a68e29375454c7","parentId":null,"modified":1713841100893,"created":1713841100893,"name":"cars-api","description":"","scope":"collection","_type":"workspace"},{"_id":"req_e9a6ef56505946bebb32b1195f412967","parentId":"wrk_2f69f9c44fea4e6193a68e29375454c7","modified":1713843153151,"created":1713843149468,"url":"http://localhost:3000/cars/menosModelos","name":"menosModelos","description":"","method":"GET","body":{},"parameters":[],"headers":[{"name":"User-Agent","value":"insomnia/8.6.1"}],"authentication":{},"metaSortKey":-1713842099154,"isPrivate":false,"pathParameters":[],"settingStoreCookies":true,"settingSendCookies":true,"settingDisableRenderRequestBody":false,"settingEncodeUrl":true,"settingRebuildPath":true,"settingFollowRedirects":"global","_type":"request"},{"_id":"req_6121d9f8b4ae44af9d1b7a06746bd9bf","parentId":"wrk_2f69f9c44fea4e6193a68e29375454c7","modified":1713885368383,"created":1713843167293,"url":"http://localhost:3000/cars/listaMaisModelos/10","name":"listaMaisModelos/:count","description":"","method":"GET","body":{},"parameters":[],"headers":[{"name":"User-Agent","value":"insomnia/8.6.1"}],"authentication":{},"metaSortKey":-1713841604959,"isPrivate":false,"pathParameters":[],"settingStoreCookies":true,"settingSendCookies":true,"settingDisableRenderRequestBody":false,"settingEncodeUrl":true,"settingRebuildPath":true,"settingFollowRedirects":"global","_type":"request"},{"_id":"req_5dff656ef7624674ab7aa3547ad4350e","parentId":"wrk_2f69f9c44fea4e6193a68e29375454c7","modified":1713885636113,"created":1713843189791,"url":"http://localhost:3000/cars//listaMenosModelos/10","name":"listaMenosModelos/:count","description":"","method":"GET","body":{},"parameters":[],"headers":[{"name":"User-Agent","value":"insomnia/8.6.1"}],"authentication":{},"metaSortKey":-1713841357861.5,"isPrivate":false,"pathParameters":[],"settingStoreCookies":true,"settingSendCookies":true,"settingDisableRenderRequestBody":false,"settingEncodeUrl":true,"settingRebuildPath":true,"settingFollowRedirects":"global","_type":"request"},{"_id":"req_97a98ded184d4dd7894d76fe33f50388","parentId":"wrk_2f69f9c44fea4e6193a68e29375454c7","modified":1713885885248,"created":1713841110764,"url":"http://localhost:3000/cars/listaModelos","name":"listaModelos","description":"","method":"POST","body":{"mimeType":"application/json","text":"{\n\t\"nomeMarca\": \"Hummer\"\n}"},"parameters":[],"headers":[{"name":"Content-Type","value":"application/json"},{"name":"User-Agent","value":"insomnia/8.6.1"}],"authentication":{},"metaSortKey":-1713841110764,"isPrivate":false,"pathParameters":[],"settingStoreCookies":true,"settingSendCookies":true,"settingDisableRenderRequestBody":false,"settingEncodeUrl":true,"settingRebuildPath":true,"settingFollowRedirects":"global","_type":"request"},{"_id":"env_e54d42a9f29a68051c4d36baa1ab15115d4c7b08","parentId":"wrk_2f69f9c44fea4e6193a68e29375454c7","modified":1713841100898,"created":1713841100898,"name":"Base Environment","data":{},"dataPropertyOrder":null,"color":null,"isPrivate":false,"metaSortKey":1713841100898,"_type":"environment"},{"_id":"jar_e54d42a9f29a68051c4d36baa1ab15115d4c7b08","parentId":"wrk_2f69f9c44fea4e6193a68e29375454c7","modified":1713841100899,"created":1713841100899,"name":"Default Jar","cookies":[],"_type":"cookie_jar"}]}